taus3/__init__.py
taus3-0.0.4.dist-info/LICENSE.txt
taus3-0.0.4.dist-info/METADATA
taus3-0.0.4.dist-info/WHEEL
taus3-0.0.4.dist-info/top_level.txt
taus3-0.0.4.dist-info/RECORD
